jupyter_browser_clipboard.py
jupyter_browser_clipboard-0.1.2.dist-info/LICENSE
jupyter_browser_clipboard-0.1.2.dist-info/METADATA
jupyter_browser_clipboard-0.1.2.dist-info/WHEEL
jupyter_browser_clipboard-0.1.2.dist-info/RECORD
