Metadata-Version: 2.1
Name: jupyter-browser-clipboard
Version: 0.1.2
Summary: Copy text to OS clipboard when using Jupyter remotely
Home-page: https://github.com/bsdz/jupyter_browser_clipboard
License: MIT
Author: Blair Azzopardi
Author-email: blairuk@gmail.com
Requires-Python: >=3.7,<4.0
Classifier: License :: OSI Approved :: MIT License
Classifier: Programming Language :: Python :: 3
Classifier: Programming Language :: Python :: 3.7
Classifier: Programming Language :: Python :: 3.8
Classifier: Programming Language :: Python :: 3.9
Classifier: Programming Language :: Python :: 3.10
Classifier: Programming Language :: Python :: 3.11
Requires-Dist: ipython
Project-URL: Repository, https://github.com/bsdz/jupyter_browser_clipboard
